.pylintrc
.testr.conf
CONTRIBUTING.rst
HACKING.rst
LICENSE
MANIFEST.in
README.rst
TESTING.rst
babel.cfg
openstack-common.conf
requirements.txt
run_tests.sh
setup.cfg
setup.py
test-requirements.txt
tox.ini
doc/source/conf.py
doc/source/contributing.rst
doc/source/index.rst
doc/source/installation.rst
doc/source/readme.rst
doc/source/usage.rst
etc/policy.json
etc/neutron/plugins/ml2/ml2_conf_seamicro.ini
seamicro_ml2/__init__.py
seamicro_ml2.egg-info/PKG-INFO
seamicro_ml2.egg-info/SOURCES.txt
seamicro_ml2.egg-info/dependency_links.txt
seamicro_ml2.egg-info/entry_points.txt
seamicro_ml2.egg-info/not-zip-safe
seamicro_ml2.egg-info/pbr.json
seamicro_ml2.egg-info/requires.txt
seamicro_ml2.egg-info/top_level.txt
seamicro_ml2/common/__init__.py
seamicro_ml2/common/client.py
seamicro_ml2/db/__init__.py
seamicro_ml2/db/models.py
seamicro_ml2/ml2/README.seamicro
seamicro_ml2/ml2/__init__.py
seamicro_ml2/ml2/mech_driver.py
seamicro_ml2/tests/__init__.py
seamicro_ml2/tests/unit/__init__.py
seamicro_ml2/tests/unit/db/__init__.py
seamicro_ml2/tests/unit/db/test_seamicro_db.py
tools/check_bash.sh
tools/check_i18n.py
tools/check_i18n_test_case.txt
tools/clean.sh
tools/i18n_cfg.py
tools/install_venv.py
tools/install_venv_common.py
tools/pretty_tox.sh
tools/subunit-trace.py
tools/with_venv.sh