Metadata-Version: 1.1
Name: seamicro-ml2
Version: 2015.1.dev1
Summary: OpenStack Networking
Home-page: https://github.com/seamicro/seamicro-ml2
Author: AMD
Author-email: harshada.kakad@izeltech.com
License: UNKNOWN
Platform: UNKNOWN
Classifier: Environment :: OpenStack
Classifier: Intended Audience :: Information Technology
Classifier: Intended Audience :: System Administrators
Classifier: License :: OSI Approved :: Apache Software License
Classifier: Operating System :: POSIX :: Linux
Classifier: Programming Language :: Python
Classifier: Programming Language :: Python :: 2
Classifier: Programming Language :: Python :: 2.7
